rqadeforestation/__init__.py
rqadeforestation/lib/rqatrend.o
rqadeforestation/lib/rqatrend.so
rqadeforestation-0.2.3.dist-info/licenses/LICENSE
rqadeforestation-0.2.3.dist-info/METADATA
rqadeforestation-0.2.3.dist-info/WHEEL
rqadeforestation-0.2.3.dist-info/top_level.txt
rqadeforestation-0.2.3.dist-info/RECORD
