Metadata-Version: 2.4
Name: rqadeforestation
Version: 0.2.3
Summary: Python package for RQA trend calculation for deforestation analysis
Author: Felix Cremer, Stephan Sahm
Author-email: Daniel Loos <dloos@bgc-jena.mpg.de>
License-Expression: MIT
Project-URL: Homepage, https://github.com/EarthyScience/RQADeforestation.py
Project-URL: Issues, https://github.com/EarthyScience/RQADeforestation.py/issues
Classifier: Programming Language :: Python :: 3
Classifier: Operating System :: POSIX :: Linux
Requires-Python: >=3.8
License-File: LICENSE
Requires-Dist: numpy
Requires-Dist: dask
Requires-Dist: xarray
Dynamic: license-file
